MANIFEST.in
README.md
setup.py
database_connection/__init__.py
database_connection/database_connection.py
database_connection.egg-info/PKG-INFO
database_connection.egg-info/SOURCES.txt
database_connection.egg-info/dependency_links.txt
database_connection.egg-info/not-zip-safe
database_connection.egg-info/requires.txt
database_connection.egg-info/top_level.txt