Metadata-Version: 1.0
Name: database-connection
Version: 0.1.1
Summary: A sqlalchemy connection utility
Home-page: http://github.com/kkwanyang/database_connection
Author: kkwanyang
Author-email: kk.dsdev@gmail.com
License: MIT
Platform: UNKNOWN
